setup.py
rotate/__init__.py
rotate/randomize.py
rotate/rotate_scamper.py
rotate/rotate_targets.py
rotate/scampertrace.py
rotate/utils.py
rotate_scamper.egg-info/PKG-INFO
rotate_scamper.egg-info/SOURCES.txt
rotate_scamper.egg-info/dependency_links.txt
rotate_scamper.egg-info/entry_points.txt
rotate_scamper.egg-info/not-zip-safe
rotate_scamper.egg-info/top_level.txt