Metadata-Version: 1.2
Name: rotate-scamper
Version: 0.0.3
Summary: Create prefix-to-AS mappings.
Home-page: https://github.com/alexmarder/traceutils
Author: Alex Marder
License: UNKNOWN
Platform: UNKNOWN
Requires-Python: >3.7
